lockdown_protocol_extra_bot/__init__.py
lockdown_protocol_extra_bot/distribute_challenges.py
lockdown_protocol_extra_bot/gen_challenges.py
lockdown_protocol_extra_bot/main.py
lockdown_protocol_extra_bot/parsing.py
lockdown_protocol_extra_bot/settings_handler.py
lockdown_protocol_extra_bot/telegram_bot.py
lockdown_protocol_extra_bot-0.0.4.dist-info/LICENSE
lockdown_protocol_extra_bot-0.0.4.dist-info/METADATA
lockdown_protocol_extra_bot-0.0.4.dist-info/WHEEL
lockdown_protocol_extra_bot-0.0.4.dist-info/entry_points.txt
lockdown_protocol_extra_bot-0.0.4.dist-info/top_level.txt
lockdown_protocol_extra_bot-0.0.4.dist-info/RECORD
